shipengine/__init__.py
shipengine/enums/__init__.py
shipengine/enums/country.py
shipengine/enums/error_code.py
shipengine/enums/error_source.py
shipengine/enums/error_type.py
shipengine/enums/regex_patterns.py
shipengine/errors/__init__.py
shipengine/http_client/__init__.py
shipengine/http_client/client.py
shipengine/shipengine.py
shipengine/shipengine_config.py
shipengine/util/__init__.py
shipengine/util/sdk_assertions.py
shipengine/version.py
shipengine-2.0.5.dist-info/METADATA
shipengine-2.0.5.dist-info/WHEEL
shipengine-2.0.5.dist-info/licenses/LICENSE
shipengine-2.0.5.dist-info/RECORD
