Metadata-Version: 2.4
Name: shipengine
Version: 2.0.5
Summary: The official Python library for ShipEngine API.
License: Apache-2.0
License-File: LICENSE
Author: ShipEngine
Author-email: support@shipengine.com
Requires-Python: >=3.10,<4.0
Classifier: Development Status :: 5 - Production/Stable
Classifier: Intended Audience :: Developers
Classifier: License :: OSI Approved :: Apache Software License
Classifier: License :: OSI Approved :: MIT License
Classifier: Natural Language :: English
Classifier: Programming Language :: Python
Classifier: Programming Language :: Python :: 3
Classifier: Programming Language :: Python :: 3.10
Classifier: Programming Language :: Python :: 3.11
Classifier: Programming Language :: Python :: 3.12
Classifier: Programming Language :: Python :: 3.13
Classifier: Programming Language :: Python :: 3.14
Classifier: Programming Language :: Python :: Implementation :: CPython
Classifier: Topic :: Software Development :: Libraries :: Python Modules
Requires-Dist: aiohttp (>=3.9.0,<4.0.0)
Requires-Dist: dataclasses-json (>=0.5.3,<0.6.0)
Requires-Dist: fuuid (>=0.1.0,<0.2.0)
Requires-Dist: poetry-dynamic-versioning (>=0.13.0,<0.14.0)
Requires-Dist: python-dotenv (>=0.15.0,<0.16.0)
Requires-Dist: requests (>=2.25.1,<3.0.0)
Project-URL: Homepage, https://www.shipengine.com/
Project-URL: Repository, https://github.com/ShipEngine/shipengine-python
